mcot/__init__.py
mcot/cifti/README.rst
mcot/cifti/VERSION
mcot/cifti/__init__.py
mcot/cifti/cifti.py
mcot/cifti/cmd.py
mcot/cifti/greyordinate.py
mcot/cifti/_scripts/__init__.py
mcot/cifti/_scripts/cifti/__init__.py
mcot/cifti/_scripts/cifti/convert.py
mcot/cifti/_scripts/cifti/correlate.py
mcot/cifti/_scripts/cifti/gradient.py
mcot/cifti/_scripts/cifti/ptx2dconn.py
mcot/cifti/_scripts/cifti/smooth.py
mcot/cifti/_scripts/function/__init__.py
mcot/cifti/_scripts/function/normalize.py
mcot/cifti/_scripts/parcel/__init__.py
mcot/cifti/_scripts/parcel/__main__.py
mcot/cifti/_scripts/parcel/cluster.py
mcot/cifti/_scripts/parcel/combine.py
mcot/cifti/_scripts/parcel/discretise.py
mcot/cifti/_scripts/parcel/random.py
mcot/cifti/_scripts/parcel/spectral.py
mcot.cifti-0.1.1.dist-info/METADATA
mcot.cifti-0.1.1.dist-info/WHEEL
mcot.cifti-0.1.1.dist-info/namespace_packages.txt
mcot.cifti-0.1.1.dist-info/top_level.txt
mcot.cifti-0.1.1.dist-info/RECORD
